semithuesystem/__init__.py
semithuesystem/alphabet.py
semithuesystem/rules_dictionary.py
semithuesystem/semi_thue_system.py
semithuesystem-1.0.2.dist-info/WHEEL
semithuesystem-1.0.2.dist-info/METADATA
semithuesystem-1.0.2.dist-info/RECORD
